README.md
setup.py
pyramid_subscribers_cookiexfer/__init__.py
pyramid_subscribers_cookiexfer.egg-info/PKG-INFO
pyramid_subscribers_cookiexfer.egg-info/SOURCES.txt
pyramid_subscribers_cookiexfer.egg-info/dependency_links.txt
pyramid_subscribers_cookiexfer.egg-info/not-zip-safe
pyramid_subscribers_cookiexfer.egg-info/requires.txt
pyramid_subscribers_cookiexfer.egg-info/top_level.txt