Metadata-Version: 1.1
Name: pyramid-subscribers-cookiexfer
Version: 0.1.1
Summary: transfers cookies from request to response on exceptions
Home-page: https://github.com/jvanasco/pyramid_subscribers_cookiexfer
Author: Jonathan Vanasco
Author-email: jonathan@findmeon.com
License: MIT
Keywords: web pyramid
Platform: UNKNOWN
Classifier: Intended Audience :: Developers
Classifier: Framework :: Pyramid
Classifier: Programming Language :: Python
Classifier: Programming Language :: Python :: 2
Classifier: Programming Language :: Python :: 3
Classifier: License :: OSI Approved :: MIT License
